xsendfile_middleware/__init__.py
xsendfile_middleware/test.py
xsendfile_middleware-0.1.1.dist-info/DESCRIPTION.rst
xsendfile_middleware-0.1.1.dist-info/METADATA
xsendfile_middleware-0.1.1.dist-info/RECORD
xsendfile_middleware-0.1.1.dist-info/WHEEL
xsendfile_middleware-0.1.1.dist-info/entry_points.txt
xsendfile_middleware-0.1.1.dist-info/metadata.json
xsendfile_middleware-0.1.1.dist-info/top_level.txt
xsendfile_middleware-0.1.1.dist-info/zip-safe
