Metadata-Version: 2.0
Name: xsendfile-middleware
Version: 0.1.1
Summary: WSGI middleware to send files using X-Accel-Redirect
Home-page: https://github.com/dairiki/xsendfile_middleware
Author: Jeff Dairiki
Author-email: dairiki@dairiki.org
License: BSD
Keywords: wsgi middleware paste x-accel-redirect nginx file_wrapper
Platform: Any
Classifier: Development Status :: 5 - Production/Stable
Classifier: Environment :: Web Environment
Classifier: Framework :: Paste
Classifier: Framework :: Pyramid
Classifier: Intended Audience :: Developers
Classifier: Intended Audience :: System Administrators
Classifier: License :: OSI Approved :: BSD License
Classifier: Programming Language :: Python :: 2.6
Classifier: Programming Language :: Python :: 2.7
Classifier: Programming Language :: Python :: 3.3
Classifier: Programming Language :: Python :: 3.4
Classifier: Programming Language :: Python :: 3.5
Classifier: Programming Language :: Python :: Implementation :: CPython
Classifier: Programming Language :: Python :: Implementation :: PyPy
Classifier: Topic :: Internet :: WWW/HTTP :: WSGI :: Middleware
